CHANGELOG.txt
LICENSE.txt
MANIFEST.in
PKG-INFO
README.txt
__init__.py
setup.cfg
setup.py
TOPSIS_101903452.egg-info/PKG-INFO
TOPSIS_101903452.egg-info/SOURCES.txt
TOPSIS_101903452.egg-info/dependency_links.txt
TOPSIS_101903452.egg-info/requires.txt
TOPSIS_101903452.egg-info/top_level.txt
dist/TOPSIS-101903452-0.0.1.tar.gz
topsis/101903452-data.csv
topsis/101903452-result-1.csv
topsis/101903452-result-2.csv
topsis/101903452.py