Metadata-Version: 2.1
Name: TOPSIS-101903452
Version: 0.0.2
Summary: A Python package to find TOPSIS for Multi-Criteria Decision Analysis Method
Home-page: https://github.com/Priya2123/Topsis
Author: Priya Aggarwal
Author-email: aggarwalpriya1121@gmail.com
License: MIT
Download-URL: https://github.com/Priya2123/Topsis/archive/refs/tags/0.0.2.tar.gz
Keywords: topsis,UCS654,TIET
Platform: UNKNOWN
Classifier: Development Status :: 3 - Alpha
Classifier: Intended Audience :: Developers
Classifier: Operating System :: Microsoft :: Windows :: Windows 10
Classifier: License :: OSI Approved :: MIT License
Classifier: Programming Language :: Python :: 3
